setup.py
tsupytero/__init__.py
tsupytero/core.py
tsupytero.egg-info/PKG-INFO
tsupytero.egg-info/SOURCES.txt
tsupytero.egg-info/dependency_links.txt
tsupytero.egg-info/requires.txt
tsupytero.egg-info/top_level.txt