Metadata-Version: 1.1
Name: tsupytero
Version: 0.1
Summary: Python wrapper for PSE stock quotes 
Home-page: https://github.com/makmac213/tsupytero
Author: Mark Allan B Meriales
Author-email: mark.meriales@gmail.com
License: UNKNOWN
Download-URL: https://github.com/makmac213/tsupytero
Platform: UNKNOWN
Classifier: Development Status :: 4 - Beta
Classifier: Intended Audience :: Developers
Classifier: Natural Language :: English
Classifier: Programming Language :: Python
Classifier: License :: Freeware
